<databaseChangeLog xmlns:xsi="http://www.w3.org/2001/XMLSchema-instance"
                   xmlns="http://www.liquibase.org/xml/ns/dbchangelog"
                   xsi:schemaLocation="http://www.liquibase.org/xml/ns/dbchangelog
   http://www.liquibase.org/xml/ns/dbchangelog/dbchangelog-3.4.xsd">

    <changeSet id="v1-1" author="lxqtpr">
        <createTable tableName="user_entity">
            <column name="id" type="UUID">
                <constraints primaryKey="true"/>
            </column>
            <column name="username" type="varchar(255)">
                <constraints nullable="false" unique="true"/>
            </column>
            <column name="password" type="varchar(255)">
                <constraints nullable="false"/>
            </column>
            <column name="role" type="varchar(255)">
                <constraints nullable="false"/>
            </column>
        </createTable>
        <sql>ALTER TABLE user_entity ADD CONSTRAINT check_role check (role in ('ROLE_ADMIN','ROLE_USER'))</sql>
    </changeSet>


</databaseChangeLog>